{
"updated":"2023-03-13T09:21:00.000Z",
"categories":
	["confession", "exhortation", "imprecation", "intercession", "lament", "other", "praise", "repentance", "supplication", "thanksgiving"],
"types":
	["command", "direct", "instruction", "reported"],
	
"total-prayers":"1234567890",

"data": {
	"prayers":[
		{
		"id":"632",
		"category":["intercession"],
		"type":["reported"],
		"testament":"new",
		"title":"null",
		"book":"3 John",
		"chapter":"1",
		"verse":"2",
		"verse-count":"1",
		"reference":"3 John 1:2",
		"asv":"Beloved, I pray that in all things thou mayest prosper and be in health, even as thy soul prospereth.",
		"asv-length":"19",
		"kjv":"Beloved, I wish above all things that thou mayest prosper and be in health, even as thy soul prospereth.",
		"kjv-length":"19",
        "related": ["null"],
        "context": "null",
		"break":"false",
		"emulate":"true",
        "person": "1",
		"next":"633",
		"previous":"631",
        "comment": "Translations are not in agreement as to whether this should be considered a prayer. Several translate the Greek 'euchomai' (Strong's 2172) to 'wish' or 'hope' instead of 'prayer.'"
		},
		{
		"id":"633",
		"category":[],
		"type":[],
		"testament":"new",
		"title":"null",
		"book":"",
		"chapter":"",
		"verse":"",
		"verse-count":"",
		"reference":"",
		"asv":"",
		"asv-length":"",
		"kjv":"",
		"kjv-length":"",
		"related": [],
		"context": "null",
		"break":"false",
		"emulate":"true",
		"person": "1",
		"next":"632",
		"previous":"634",
		"comment": "null"
		}]
	}
}
